38decoder/top_synth.v
/* Generated by Yosys 0.33 (git sha1 2584903a060) */

module decode3_8(din, dout);
  wire \$abc$163$din[0] ;
  wire \$abc$163$din[1] ;
  wire \$abc$163$din[2] ;
  wire \$abc$163$dout[0] ;
  wire \$abc$163$dout[1] ;
  wire \$abc$163$dout[2] ;
  wire \$abc$163$dout[3] ;
  wire \$abc$163$dout[4] ;
  wire \$abc$163$dout[5] ;
  wire \$abc$163$dout[6] ;
  wire \$abc$163$dout[7] ;
  wire \$abc$163$new_n12_ ;
  wire \$abc$163$new_n13_ ;
  wire \$abc$163$new_n14_ ;
  wire \$abc$163$new_n15_ ;
  wire \$abc$163$new_n17_ ;
  wire \$abc$163$new_n19_ ;
  wire \$abc$163$new_n21_ ;
  wire [7:0] \$memory$auto$proc_rom.cc:150:do_switch$3$rdmux[0][0][0]$a$10 ;
  wire [7:0] \$memory$auto$proc_rom.cc:150:do_switch$3$rdmux[0][1][0]$a$13 ;
  input [2:0] din;
  wire [2:0] din;
  output [7:0] dout;
  wire [7:0] dout;
  assign \$abc$163$new_n12_  = ~\$abc$163$din[1] ;
  assign \$abc$163$new_n13_  = ~\$abc$163$din[0] ;
  assign \$abc$163$new_n14_  = ~\$abc$163$din[2] ;
  assign \$abc$163$new_n15_  = \$abc$163$new_n12_  & \$abc$163$new_n13_ ;
  assign \$abc$163$dout[0]  = \$abc$163$new_n14_  & \$abc$163$new_n15_ ;
  assign \$abc$163$new_n17_  = \$abc$163$new_n12_  & \$abc$163$din[0] ;
  assign \$abc$163$dout[1]  = \$abc$163$new_n14_  & \$abc$163$new_n17_ ;
  assign \$abc$163$new_n19_  = \$abc$163$din[1]  & \$abc$163$new_n13_ ;
  assign \$abc$163$dout[2]  = \$abc$163$new_n14_  & \$abc$163$new_n19_ ;
  assign \$abc$163$new_n21_  = \$abc$163$din[1]  & \$abc$163$din[0] ;
  assign \$abc$163$dout[3]  = \$abc$163$new_n14_  & \$abc$163$new_n21_ ;
  assign \$abc$163$dout[4]  = \$abc$163$din[2]  & \$abc$163$new_n15_ ;
  assign \$abc$163$dout[5]  = \$abc$163$din[2]  & \$abc$163$new_n17_ ;
  assign \$abc$163$dout[6]  = \$abc$163$din[2]  & \$abc$163$new_n19_ ;
  assign \$abc$163$dout[7]  = \$abc$163$din[2]  & \$abc$163$new_n21_ ;
  assign \$memory$auto$proc_rom.cc:150:do_switch$3$rdmux[0][0][0]$a$10 [7:4] = 4'h0;
  assign \$memory$auto$proc_rom.cc:150:do_switch$3$rdmux[0][1][0]$a$13 [7:1] = { 6'h00, din[0] };
  assign \$abc$163$din[1]  = din[1];
  assign \$abc$163$din[0]  = din[0];
  assign \$abc$163$din[2]  = din[2];
  assign dout[0] = \$abc$163$dout[0] ;
  assign dout[1] = \$abc$163$dout[1] ;
  assign dout[2] = \$abc$163$dout[2] ;
  assign dout[3] = \$abc$163$dout[3] ;
  assign dout[4] = \$abc$163$dout[4] ;
  assign dout[5] = \$abc$163$dout[5] ;
  assign dout[6] = \$abc$163$dout[6] ;
  assign dout[7] = \$abc$163$dout[7] ;
endmodule

38decoder/tb.v
`timescale 1ns/1ps
module tb_decode3_8;
   reg [2:0] din;
   wire [7:0] dout;
   initial begin
      $dumpfile("wave.vcd");
      $dumpvars(0,tb_decode3_8);
      //Initialize Iinputs
      din=0;
      #100 din=1;
      #100 din=2;
      #100 din=3;
      #100 din=4;
      #100 din=5;
      #100 din=6;
      #100 din=7;
      end
decode3_8 u1(
     .din(din),
     .dout(dout));
endmodule

38decoder/wave.vcd
$date
	Fri Jan 30 22:36:43 2026
$end
$version
	Icarus Verilog
$end
$timescale
	1ps
$end
$scope module tb_decode3_8 $end
$var wire 8 ! dout [7:0] $end
$var reg 3 " din [2:0] $end
$scope module u1 $end
$var wire 3 # din [2:0] $end
$var reg 8 $ dout [7:0] $end
$upscope $end
$upscope $end
$enddefinitions $end
$comment Show the parameter values. $end
$dumpall
$end
#0
$dumpvars
b1 $
b0 #
b0 "
b1 !
$end
#100000
b10 !
b10 $
b1 "
b1 #
#200000
b100 !
b100 $
b10 "
b10 #
#300000
b1000 !
b1000 $
b11 "
b11 #
#400000
b10000 !
b10000 $
b100 "
b100 #
#500000
b100000 !
b100000 $
b101 "
b101 #
#600000
b1000000 !
b1000000 $
b110 "
b110 #
#700000
b10000000 !
b10000000 $
b111 "
b111 #
