counter/loop_counter.v
module loop_counter(
	      clk,
	      resetn,
	      out1,
	       out0);
   input clk;
   input resetn;
   output reg [3:0] out0;
   output reg [3:0] out1;
   
   always @(posedge clk or negedge resetn)
     if(!resetn) begin
       out1<=4'b0000;
       out0<=4'b0000;
     end
     else begin
	if (out0==9)  begin
	   out0<=0;
	   if(out1==9)begin
	      out1<=0;
	   end
	   else begin
	      out1<=out1+1;
	   end
	end
	else begin
	   out0<=out0+1;
	end
     end // else: !if(!resetn)
   endmodule

counter/tb_loop_counter.v
// 1. timescale指令必须在模块定义之前
`timescale 1ns/1ps

module tb_loop_counter;
    reg clk;
    reg resetn;
    wire [3:0] out1;
    wire [3:0] out0;
    
    // 实例化被测试模块
    loop_counter ul(
        .clk(clk),
        .resetn(resetn),
        .out1(out1),
        .out0(out0)
    );
    
    // 时钟生成
    initial begin
        clk = 0;
        forever #10 clk = ~clk;
    end
    
    // 测试序列
    initial begin
        $dumpfile("wave.vcd");
        $dumpvars(0, tb_loop_counter);
        
        resetn = 0;  // 初始复位
        
        #20 resetn = 1;  // 释放复位
        
        #2100 $finish;  // 仿真结束
    end
    
endmodule  // 确保模块有结束标记

counter/wave.vcd
$date
	Thu Feb  5 23:16:24 2026
$end
$version
	Icarus Verilog
$end
$timescale
	1ps
$end
$scope module tb_loop_counter $end
$var wire 4 ! out1 [3:0] $end
$var wire 4 " out0 [3:0] $end
$var reg 1 # clk $end
$var reg 1 $ resetn $end
$scope module ul $end
$var wire 1 # clk $end
$var wire 1 $ resetn $end
$var reg 4 % out0 [3:0] $end
$var reg 4 & out1 [3:0] $end
$upscope $end
$upscope $end
$enddefinitions $end
$comment Show the parameter values. $end
$dumpall
$end
#0
$dumpvars
b0 &
b0 %
0$
0#
b0 "
b0 !
$end
#10000
1#
#20000
0#
1$
#30000
b1 "
b1 %
1#
#40000
0#
#50000
b10 "
b10 %
1#
#60000
0#
#70000
b11 "
b11 %
1#
#80000
0#
#90000
b100 "
b100 %
1#
#100000
0#
#110000
b101 "
b101 %
1#
#120000
0#
#130000
b110 "
b110 %
1#
#140000
0#
#150000
b111 "
b111 %
1#
#160000
0#
#170000
b1000 "
b1000 %
1#
#180000
0#
#190000
b1001 "
b1001 %
1#
#200000
0#
#210000
b1 !
b1 &
b0 "
b0 %
1#
#220000
0#
#230000
b1 "
b1 %
1#
#240000
0#
#250000
b10 "
b10 %
1#
#260000
0#
#270000
b11 "
b11 %
1#
#280000
0#
#290000
b100 "
b100 %
1#
#300000
0#
#310000
b101 "
b101 %
1#
#320000
0#
#330000
b110 "
b110 %
1#
#340000
0#
#350000
b111 "
b111 %
1#
#360000
0#
#370000
b1000 "
b1000 %
1#
#380000
0#
#390000
b1001 "
b1001 %
1#
#400000
0#
#410000
b10 !
b10 &
b0 "
b0 %
1#
#420000
0#
#430000
b1 "
b1 %
1#
#440000
0#
#450000
b10 "
b10 %
1#
#460000
0#
#470000
b11 "
b11 %
1#
#480000
0#
#490000
b100 "
b100 %
1#
#500000
0#
#510000
b101 "
b101 %
1#
#520000
0#
#530000
b110 "
b110 %
1#
#540000
0#
#550000
b111 "
b111 %
1#
#560000
0#
#570000
b1000 "
b1000 %
1#
#580000
0#
#590000
b1001 "
b1001 %
1#
#600000
0#
#610000
b11 !
b11 &
b0 "
b0 %
1#
#620000
0#
#630000
b1 "
b1 %
1#
#640000
0#
#650000
b10 "
b10 %
1#
#660000
0#
#670000
b11 "
b11 %
1#
#680000
0#
#690000
b100 "
b100 %
1#
#700000
0#
#710000
b101 "
b101 %
1#
#720000
0#
#730000
b110 "
b110 %
1#
#740000
0#
#750000
b111 "
b111 %
1#
#760000
0#
#770000
b1000 "
b1000 %
1#
#780000
0#
#790000
b1001 "
b1001 %
1#
#800000
0#
#810000
b100 !
b100 &
b0 "
b0 %
1#
#820000
0#
#830000
b1 "
b1 %
1#
#840000
0#
#850000
b10 "
b10 %
1#
#860000
0#
#870000
b11 "
b11 %
1#
#880000
0#
#890000
b100 "
b100 %
1#
#900000
0#
#910000
b101 "
b101 %
1#
#920000
0#
#930000
b110 "
b110 %
1#
#940000
0#
#950000
b111 "
b111 %
1#
#960000
0#
#970000
b1000 "
b1000 %
1#
#980000
0#
#990000
b1001 "
b1001 %
1#
#1000000
0#
#1010000
b101 !
b101 &
b0 "
b0 %
1#
#1020000
0#
#1030000
b1 "
b1 %
1#
#1040000
0#
#1050000
b10 "
b10 %
1#
#1060000
0#
#1070000
b11 "
b11 %
1#
#1080000
0#
#1090000
b100 "
b100 %
1#
#1100000
0#
#1110000
b101 "
b101 %
1#
#1120000
0#
#1130000
b110 "
b110 %
1#
#1140000
0#
#1150000
b111 "
b111 %
1#
#1160000
0#
#1170000
b1000 "
b1000 %
1#
#1180000
0#
#1190000
b1001 "
b1001 %
1#
#1200000
0#
#1210000
b110 !
b110 &
b0 "
b0 %
1#
#1220000
0#
#1230000
b1 "
b1 %
1#
#1240000
0#
#1250000
b10 "
b10 %
1#
#1260000
0#
#1270000
b11 "
b11 %
1#
#1280000
0#
#1290000
b100 "
b100 %
1#
#1300000
0#
#1310000
b101 "
b101 %
1#
#1320000
0#
#1330000
b110 "
b110 %
1#
#1340000
0#
#1350000
b111 "
b111 %
1#
#1360000
0#
#1370000
b1000 "
b1000 %
1#
#1380000
0#
#1390000
b1001 "
b1001 %
1#
#1400000
0#
#1410000
b111 !
b111 &
b0 "
b0 %
1#
#1420000
0#
#1430000
b1 "
b1 %
1#
#1440000
0#
#1450000
b10 "
b10 %
1#
#1460000
0#
#1470000
b11 "
b11 %
1#
#1480000
0#
#1490000
b100 "
b100 %
1#
#1500000
0#
#1510000
b101 "
b101 %
1#
#1520000
0#
#1530000
b110 "
b110 %
1#
#1540000
0#
#1550000
b111 "
b111 %
1#
#1560000
0#
#1570000
b1000 "
b1000 %
1#
#1580000
0#
#1590000
b1001 "
b1001 %
1#
#1600000
0#
#1610000
b1000 !
b1000 &
b0 "
b0 %
1#
#1620000
0#
#1630000
b1 "
b1 %
1#
#1640000
0#
#1650000
b10 "
b10 %
1#
#1660000
0#
#1670000
b11 "
b11 %
1#
#1680000
0#
#1690000
b100 "
b100 %
1#
#1700000
0#
#1710000
b101 "
b101 %
1#
#1720000
0#
#1730000
b110 "
b110 %
1#
#1740000
0#
#1750000
b111 "
b111 %
1#
#1760000
0#
#1770000
b1000 "
b1000 %
1#
#1780000
0#
#1790000
b1001 "
b1001 %
1#
#1800000
0#
#1810000
b1001 !
b1001 &
b0 "
b0 %
1#
#1820000
0#
#1830000
b1 "
b1 %
1#
#1840000
0#
#1850000
b10 "
b10 %
1#
#1860000
0#
#1870000
b11 "
b11 %
1#
#1880000
0#
#1890000
b100 "
b100 %
1#
#1900000
0#
#1910000
b101 "
b101 %
1#
#1920000
0#
#1930000
b110 "
b110 %
1#
#1940000
0#
#1950000
b111 "
b111 %
1#
#1960000
0#
#1970000
b1000 "
b1000 %
1#
#1980000
0#
#1990000
b1001 "
b1001 %
1#
#2000000
0#
#2010000
b0 !
b0 &
b0 "
b0 %
1#
#2020000
0#
#2030000
b1 "
b1 %
1#
#2040000
0#
#2050000
b10 "
b10 %
1#
#2060000
0#
#2070000
b11 "
b11 %
1#
#2080000
0#
#2090000
b100 "
b100 %
1#
#2100000
0#
#2110000
b101 "
b101 %
1#
