8_rainbow_light_contrallor/8_rainbow_light.v
module eight_rainbow_light(
		       clk,
		       rst,
		       control,
		       dout);
   input clk;
   input rst;
   input control;
   output reg [7:0] dout;
   // Mode A states
parameter A0 = 4'd0, A1=4'd1, A2=4'd2, A3=4'd3,
          A4=4'd4, A5=4'd5, A6=4'd6, A7=4'd7,
          A8=4'd8, A9=4'd9, A10=4'd10, A11=4'd11,
          A12=4'd12, A13=4'd13, A14=4'd14, A15=4'd15;
   // Mode B states
   parameter B0 = 2'b0;
   parameter B1 = 2'b1;
   parameter B2 = 2'b10;
   reg [3:0] state_a, next_state_a;
   reg	[1:0]     state_b, next_state_b;

   // 状态更新（使用双边沿触发）
always @(posedge clk or negedge clk or posedge rst) begin
    if (rst) begin
        state_a <= A15;
        state_b <= B2;
        dout <= 8'b00000000;
    end else begin
        if (control) begin
            // Mode A: 使用双边沿更新
            state_a <= next_state_a;
            // 根据状态设置输出
            case (state_a)  
                A0:  dout <= 8'b00000001;
                A1:  dout <= 8'b00000011;
                A2:  dout <= 8'b00000111;
                A3:  dout <= 8'b00001111;
                A4:  dout <= 8'b00011111;
                A5:  dout <= 8'b00111111;
                A6:  dout <= 8'b01111111;
                A7:  dout <= 8'b11111111;
                A8:  dout <= 8'b11111110;
                A9:  dout <= 8'b11111100;
                A10: dout <= 8'b11111000;
                A11: dout <= 8'b11110000;
                A12: dout <= 8'b11100000;
                A13: dout <= 8'b11000000;
                A14: dout <= 8'b10000000;
                A15: dout <= 8'b00000000;
                default: dout <= 8'b00000000;
            endcase
        end else begin
            // Mode B: 使用双边沿更新
            state_b <= next_state_b;
            // 根据状态设置输出
            case (state_b)
              B0: dout <= 8'b01010101;
              B1: dout <= 8'b10101010;
	      B2: dout <= 8'b0000_0000;	      
              default: dout <= 8'b0000_0000;
            endcase
        end
    end
end

// 组合逻辑计算下一状态
always @(*) begin
    if (control) begin
        // Mode A 下一状态
        case (state_a)
            A0:  next_state_a = A1;
            A1:  next_state_a = A2;
            A2:  next_state_a = A3;
            A3:  next_state_a = A4;
            A4:  next_state_a = A5;
            A5:  next_state_a = A6;
            A6:  next_state_a = A7;
            A7:  next_state_a = A8;
            A8:  next_state_a = A9;
            A9:  next_state_a = A10;
            A10: next_state_a = A11;
            A11: next_state_a = A12;
            A12: next_state_a = A13;
            A13: next_state_a = A14;
            A14: next_state_a = A15;
            A15: next_state_a = A0;
            default: next_state_a = A15;
        endcase
    end else begin
        // Mode B 下一状态
        case (state_b)
	  B2:next_state_b  = B0;	  
          B0: next_state_b = B1;
          B1: next_state_b = B0;
          default: next_state_b = B2;
        endcase
    end // else: !if(control)
end // always @ (*)
endmodule

8_rainbow_light_contrallor/tb_8_rainbow_light.v
`timescale 1us/1us
module tb_8_rainbow_light;
   reg clk;
   reg rst;
   reg control;
   wire [7:0] dout;
   always begin 
      #500 clk=0;
      #500 clk=1;
   end
   eight_rainbow_light uut(
		       .clk(clk)
		       ,.rst(rst)
		       ,.control(control)
		       ,.dout(dout));
   initial begin
      $dumpfile("wave.vcd");
      $dumpvars(0, tb_8_rainbow_light);
      rst=1;
      control=0;     
      #1000
	rst=0;
      #1000
	control=1;
      #16000
	control=0;
      #10000
	$finish;
   end // initial begin
   endmodule

8_rainbow_light_contrallor/wave.vcd
$date
	Tue Feb 17 20:39:02 2026
$end
$version
	Icarus Verilog
$end
$timescale
	1us
$end
$scope module tb_8_rainbow_light $end
$var wire 8 ! dout [7:0] $end
$var reg 1 " clk $end
$var reg 1 # control $end
$var reg 1 $ rst $end
$scope module uut $end
$var wire 1 " clk $end
$var wire 1 # control $end
$var wire 1 $ rst $end
$var parameter 4 % A0 $end
$var parameter 4 & A1 $end
$var parameter 4 ' A10 $end
$var parameter 4 ( A11 $end
$var parameter 4 ) A12 $end
$var parameter 4 * A13 $end
$var parameter 4 + A14 $end
$var parameter 4 , A15 $end
$var parameter 4 - A2 $end
$var parameter 4 . A3 $end
$var parameter 4 / A4 $end
$var parameter 4 0 A5 $end
$var parameter 4 1 A6 $end
$var parameter 4 2 A7 $end
$var parameter 4 3 A8 $end
$var parameter 4 4 A9 $end
$var parameter 2 5 B0 $end
$var parameter 2 6 B1 $end
$var parameter 2 7 B2 $end
$var reg 8 8 dout [7:0] $end
$var reg 4 9 next_state_a [3:0] $end
$var reg 2 : next_state_b [1:0] $end
$var reg 4 ; state_a [3:0] $end
$var reg 2 < state_b [1:0] $end
$upscope $end
$upscope $end
$enddefinitions $end
$comment Show the parameter values. $end
$dumpall
b10 7
b1 6
b0 5
b1001 4
b1000 3
b111 2
b110 1
b101 0
b100 /
b11 .
b10 -
b1111 ,
b1110 +
b1101 *
b1100 )
b1011 (
b1010 '
b1 &
b0 %
$end
#0
$dumpvars
b10 <
b1111 ;
b0 :
bx 9
b0 8
1$
0#
x"
b0 !
$end
#500
0"
#1000
b1 :
b0 <
1"
0$
#1500
b0 :
b1010101 !
b1010101 8
b1 <
0"
#2000
b0 !
b0 8
b0 ;
b1 9
1"
1#
#2500
b10 9
b1 !
b1 8
b1 ;
0"
#3000
b11 9
b11 !
b11 8
b10 ;
1"
#3500
b100 9
b111 !
b111 8
b11 ;
0"
#4000
b101 9
b1111 !
b1111 8
b100 ;
1"
#4500
b110 9
b11111 !
b11111 8
b101 ;
0"
#5000
b111 9
b111111 !
b111111 8
b110 ;
1"
#5500
b1000 9
b1111111 !
b1111111 8
b111 ;
0"
#6000
b1001 9
b11111111 !
b11111111 8
b1000 ;
1"
#6500
b1010 9
b11111110 !
b11111110 8
b1001 ;
0"
#7000
b1011 9
b11111100 !
b11111100 8
b1010 ;
1"
#7500
b1100 9
b11111000 !
b11111000 8
b1011 ;
0"
#8000
b1101 9
b11110000 !
b11110000 8
b1100 ;
1"
#8500
b1110 9
b11100000 !
b11100000 8
b1101 ;
0"
#9000
b1111 9
b11000000 !
b11000000 8
b1110 ;
1"
#9500
b0 9
b10000000 !
b10000000 8
b1111 ;
0"
#10000
b1 9
b0 !
b0 8
b0 ;
1"
#10500
b10 9
b1 !
b1 8
b1 ;
0"
#11000
b11 9
b11 !
b11 8
b10 ;
1"
#11500
b100 9
b111 !
b111 8
b11 ;
0"
#12000
b101 9
b1111 !
b1111 8
b100 ;
1"
#12500
b110 9
b11111 !
b11111 8
b101 ;
0"
#13000
b111 9
b111111 !
b111111 8
b110 ;
1"
#13500
b1000 9
b1111111 !
b1111111 8
b111 ;
0"
#14000
b1001 9
b11111111 !
b11111111 8
b1000 ;
1"
#14500
b1010 9
b11111110 !
b11111110 8
b1001 ;
0"
#15000
b1011 9
b11111100 !
b11111100 8
b1010 ;
1"
#15500
b1100 9
b11111000 !
b11111000 8
b1011 ;
0"
#16000
b1101 9
b11110000 !
b11110000 8
b1100 ;
1"
#16500
b1110 9
b11100000 !
b11100000 8
b1101 ;
0"
#17000
b1111 9
b11000000 !
b11000000 8
b1110 ;
1"
#17500
b0 9
b10000000 !
b10000000 8
b1111 ;
0"
#18000
b1 :
b10101010 !
b10101010 8
b0 <
1"
0#
#18500
b0 :
b1010101 !
b1010101 8
b1 <
0"
#19000
b1 :
b10101010 !
b10101010 8
b0 <
1"
#19500
b0 :
b1010101 !
b1010101 8
b1 <
0"
#20000
b1 :
b10101010 !
b10101010 8
b0 <
1"
#20500
b0 :
b1010101 !
b1010101 8
b1 <
0"
#21000
b1 :
b10101010 !
b10101010 8
b0 <
1"
#21500
b0 :
b1010101 !
b1010101 8
b1 <
0"
#22000
b1 :
b10101010 !
b10101010 8
b0 <
1"
#22500
b0 :
b1010101 !
b1010101 8
b1 <
0"
#23000
b1 :
b10101010 !
b10101010 8
b0 <
1"
#23500
b0 :
b1010101 !
b1010101 8
b1 <
0"
#24000
b1 :
b10101010 !
b10101010 8
b0 <
1"
#24500
b0 :
b1010101 !
b1010101 8
b1 <
0"
#25000
b1 :
b10101010 !
b10101010 8
b0 <
1"
#25500
b0 :
b1010101 !
b1010101 8
b1 <
0"
#26000
b1 :
b10101010 !
b10101010 8
b0 <
1"
#26500
b0 :
b1010101 !
b1010101 8
b1 <
0"
#27000
b1 :
b10101010 !
b10101010 8
b0 <
1"
#27500
b0 :
b1010101 !
b1010101 8
b1 <
0"
#28000
b1 :
b10101010 !
b10101010 8
b0 <
1"
